{"strMeasure13": "", "strIngredient9": "", "strCategory": "Coffee / Tea", "strIngredient5": "", "strMeasure11": "", "strIngredient1": "Coffee", "strMeasure4": "4 cups cold ", "strIngredient7": "", "strMeasure12": "", "strMeasure6": " ", "strMeasure5": " ", "dateModified": "2016-02-03 15:37:35", "strMeasure3": "1/4 cup hot ", "strVideo": null, "strIngredient4": "Milk", "strMeasure1": "1/4 cup instant ", "strIngredient12": "", "idDrink": "12770", "strIngredient15": "", "strMeasure15": "", "strDrinkThumb": "http://www.thecocktaildb.com/images/media/drink/ytprxy1454513855.jpg", "strMeasure2": "1/4 cup ", "strIngredient14": "", "strMeasure7": " ", "strMeasure14": "", "strIngredient6": "", "strIngredient2": "Sugar", "strIngredient13": "", "strIngredient3": "Water", "strGlass": "Coffee mug", "strIngredient11": "", "strDrink": "Iced Coffee", "strMeasure9": " ", "strMeasure8": " ", "strMeasure10": "", "strIngredient8": "", "strIngredient10": "", "strInstructions": "Mix together until coffee and sugar is dissolved. Add milk. Shake well. Using a blender or milk shake maker produces a very foamy drink. Serve in coffee mug.", "strIBA": null, "strAlcoholic": "Non alcoholic"}