{"strIngredient2": "Lemon", "strIngredient14": "", "strAlcoholic": "Alcoholic", "strMeasure2": "2 ", "strIngredient8": "", "strIngredient3": "Orange juice", "strMeasure6": " ", "strMeasure15": "", "strIngredient5": "Pineapple juice", "strInstructions": "Combine all of the ingredients and pour over a block of ice.", "strIngredient6": "", "strDrink": "Wine Punch", "strIngredient15": "", "strIngredient1": "Red wine", "strIngredient9": "", "idDrink": "13058", "strMeasure4": "3 ", "strIngredient11": "", "strIngredient13": "", "strMeasure3": "1 cup ", "strDrinkThumb": "http://www.thecocktaildb.com/images/media/drink/txustu1473344310.jpg", "strMeasure10": " ", "strMeasure13": "", "strVideo": null, "strMeasure14": "", "strMeasure7": " ", "strMeasure9": " ", "strCategory": "Punch / Party Drink", "dateModified": "2016-09-08 15:18:30", "strIngredient12": "", "strMeasure11": "", "strIngredient10": "", "strIBA": null, "strGlass": "Collins Glass", "strIngredient7": "", "strIngredient4": "Orange", "strMeasure12": "", "strMeasure5": "1 cup ", "strMeasure1": "1 bottle ", "strMeasure8": " "}