{"strIngredient14": "", "strIngredient8": "", "strVideo": null, "strIngredient4": "Creme de Banane", "strMeasure15": "", "dateModified": "2016-08-31 19:30:01", "strMeasure11": "", "strMeasure2": "2 oz ", "strMeasure9": " ", "strMeasure6": " ", "strInstructions": "Drop shot glass with banana & melon liquers into a 9 oz hi- ball glass containing soda water and cranberry juice. Drink in one shot.", "strIngredient11": "", "strIBA": null, "strIngredient7": "", "strAlcoholic": "Alcoholic", "strIngredient5": "", "strMeasure4": "0.5 oz ", "strGlass": "Highball glass", "strCategory": "Shot", "strIngredient10": "", "strIngredient2": "Soda water", "strIngredient1": "Cranberry juice", "strIngredient3": "Midori melon liqueur", "strMeasure12": "", "strIngredient6": "", "strIngredient13": "", "strIngredient15": "", "strMeasure13": "", "strDrink": "A Splash of Nash", "idDrink": "14564", "strMeasure14": "", "strMeasure8": " ", "strDrinkThumb": "http://www.thecocktaildb.com/images/media/drink/rsvtrr1472668201.jpg", "strIngredient9": "", "strMeasure7": " ", "strMeasure5": " ", "strMeasure3": "0.5 oz ", "strMeasure10": "", "strMeasure1": "2 oz ", "strIngredient12": ""}