{"strIngredient14": "", "strIngredient8": "", "strVideo": null, "strIngredient4": "", "strMeasure15": "", "dateModified": "2016-08-31 19:37:02", "strMeasure11": "", "strMeasure2": "12 oz ", "strMeasure9": "", "strMeasure6": " ", "strInstructions": "Chill both ingredients!! Mix in a tumbler and enjoy!", "strIngredient11": "", "strIBA": null, "strIngredient7": "", "strAlcoholic": "Alcoholic", "strIngredient5": "", "strMeasure4": " ", "strGlass": "Punch Bowl", "strCategory": "Punch / Party Drink", "strIngredient10": "", "strIngredient2": "Apple cider", "strIngredient1": "Tequila", "strIngredient3": "", "strMeasure12": "", "strIngredient6": "", "strIngredient13": "", "strIngredient15": "", "strMeasure13": "", "strDrink": "Apple Grande", "idDrink": "16289", "strMeasure14": "", "strMeasure8": "", "strDrinkThumb": "http://www.thecocktaildb.com/images/media/drink/wqrptx1472668622.jpg", "strIngredient9": "", "strMeasure7": " ", "strMeasure5": " ", "strMeasure3": " ", "strMeasure10": "", "strMeasure1": "3 oz ", "strIngredient12": ""}