{"strMeasure9": "", "strIngredient2": "Lemon juice", "strIngredient12": "", "strAlcoholic": "Non alcoholic", "strIngredient3": "", "strMeasure13": "", "strIngredient8": "", "strMeasure11": "", "strMeasure15": "", "strIngredient6": "", "idDrink": "17108", "strMeasure4": " ", "strMeasure3": " ", "strMeasure10": "", "strIngredient15": "", "strIngredient5": "", "strMeasure2": "7 drops ", "strVideo": null, "strMeasure1": "1 dl ", "strIngredient11": "", "strDrinkThumb": "http://www.thecocktaildb.com/images/media/drink/yrtxxp1472719367.jpg", "strDrink": "Coke and Drops", "dateModified": "2016-09-01 09:42:47", "strIngredient1": "Coca-Cola", "strMeasure5": " ", "strIngredient13": "", "strMeasure7": " ", "strMeasure8": "", "strIngredient14": "", "strGlass": "Cocktail glass", "strCategory": "Soft Drink / Soda", "strMeasure12": "", "strIngredient9": "", "strIngredient7": "", "strIBA": null, "strInstructions": "Take a glass, pour the Coke in the glass, then you take 7 drops of lemon juice. Granish with a lemon slice on the rim of the glass.", "strIngredient10": "", "strMeasure6": " ", "strMeasure14": "", "strIngredient4": ""}