{"strIngredient2": "Apricot Brandy", "strIngredient14": "", "strAlcoholic": "Alcoholic", "strMeasure2": "4 parts", "strIngredient8": "", "strIngredient3": "Orange Juice", "strMeasure6": " ", "strMeasure15": "", "strIngredient5": "", "strInstructions": "Shake together over ice. Strain into cocktail glass and serve chilled.", "strIngredient6": "", "strDrink": "Paradise", "strIngredient15": "", "strIngredient1": "Gin", "strIngredient9": "", "idDrink": "17190", "strMeasure4": " ", "strIngredient11": "", "strIngredient13": "", "strMeasure3": "3 parts ", "strDrinkThumb": "http://www.thecocktaildb.com/images/media/drink/ejozd71504351060.jpg", "strMeasure10": "", "strMeasure13": "", "strVideo": null, "strMeasure14": "", "strMeasure7": " ", "strMeasure9": "", "strCategory": "Ordinary Drink", "dateModified": "2017-09-02 12:17:40", "strIngredient12": "", "strMeasure11": "", "strIngredient10": "", "strIBA": "Unforgettables", "strGlass": "Cocktail glass", "strIngredient7": "", "strIngredient4": "", "strMeasure12": "", "strMeasure5": " ", "strMeasure1": "7 parts", "strMeasure8": ""}